quantrocket_utils/__init__.py
quantrocket_utils/utils.py
quantrocket_utils-0.1.9.dist-info/WHEEL
quantrocket_utils-0.1.9.dist-info/METADATA
quantrocket_utils-0.1.9.dist-info/RECORD
