Metadata-Version: 2.1
Name: quantrocket-utils
Version: 0.1.9
Summary: Utility methods for common tasks in QuantRocket.
Home-page: https://github.com/boosting-alpha-bv/quantrocket-utils
License: MIT
Author: Tim Wedde
Author-email: timwedde@icloud.com
Requires-Python: >=3.7,<4.0
Classifier: License :: OSI Approved :: MIT License
Classifier: Programming Language :: Python :: 3
Classifier: Programming Language :: Python :: 3.7
Requires-Dist: arrow (>=0.15.2,<0.16.0)
Requires-Dist: colorama (>=0.4.1,<0.5.0)
Requires-Dist: ib-trading-calendars (>=0.1.2,<0.2.0)
Requires-Dist: termcolor (>=1.1,<2.0)
Requires-Dist: trading-calendars (>=1.11,<2.0)
Project-URL: Repository, https://github.com/boosting-alpha-bv/quantrocket-utils
